iic2343/__init__.py
iic2343/cli/__init__.py
iic2343/cli/core.py
iic2343/cli/generators.py
iic2343/cli/utils.py
iic2343/constants.py
iic2343/core.py
iic2343/errors.py
iic2343/utils.py
iic2343-0.2.0.dist-info/entry_points.txt
iic2343-0.2.0.dist-info/LICENSE
iic2343-0.2.0.dist-info/WHEEL
iic2343-0.2.0.dist-info/METADATA
iic2343-0.2.0.dist-info/RECORD
