Metadata-Version: 2.1
Name: iic2343
Version: 0.2.0
Summary: Write to the Basys3 ROM directly.
Home-page: https://github.com/daleal/iic2343
License: MIT
Author: Daniel Leal
Author-email: dlleal@uc.cl
Maintainer: Daniel Leal
Maintainer-email: dlleal@uc.cl
Requires-Python: >=3.6,<4.0
Classifier: License :: OSI Approved :: MIT License
Classifier: Programming Language :: Python :: 3
Classifier: Programming Language :: Python :: 3.6
Classifier: Programming Language :: Python :: 3.7
Classifier: Programming Language :: Python :: 3.8
Classifier: Programming Language :: Python :: 3.9
Requires-Dist: pyserial (>=3.5,<4.0)
Project-URL: Documentation, https://github.com/daleal/iic2343#readme
Project-URL: Issue Tracker, https://github.com/daleal/iic2343/issues
Project-URL: Repository, https://github.com/daleal/iic2343
